{
  "ts": "2026-06-28T21:45:36.664Z",
  "finishedCount": 73,
  "toFetchCount": 1,
  "cacheSize": 72,
  "firstFinishedIds": [
    537417,
    537401,
    537402,
    537407,
    537408
  ],
  "toFetchCount2": 1,
  "toFetchSample": [
    537417
  ],
  "espnDates": [
    {
      "date": "2026-06-28",
      "count": 16
    }
  ],
  "espnSampleStats": [
    {
      "team": "South Africa",
      "stats": [
        "foulsCommitted=10",
        "yellowCards=0",
        "redCards=0",
        "offsides=1",
        "wonCorners=1",
        "saves=5",
        "possessionPct=58.2",
        "totalShots=6",
        "shotsOnTarget=1",
        "shotPct=0.2",
        "penaltyKickGoals=0",
        "penaltyKickShots=0",
        "accuratePasses=466",
        "totalPasses=550",
        "passPct=0.8",
        "accurateCrosses=2",
        "totalCrosses=8",
        "crossPct=0.3",
        "totalLongBalls=70",
        "accurateLongBalls=31",
        "longballPct=0.4",
        "blockedShots=1",
        "effectiveTackles=14",
        "totalTackles=23",
        "tacklePct=0.6",
        "interceptions=16",
        "effectiveClearance=34",
        "totalClearance=34"
      ]
    },
    {
      "team": "Canada",
      "stats": [
        "foulsCommitted=16",
        "yellowCards=2",
        "redCards=0",
        "offsides=0",
        "wonCorners=4",
        "saves=1",
        "possessionPct=41.8",
        "totalShots=12",
        "shotsOnTarget=7",
        "shotPct=0.6",
        "penaltyKickGoals=0",
        "penaltyKickShots=0",
        "accuratePasses=298",
        "totalPasses=381",
        "passPct=0.8",
        "accurateCrosses=5",
        "totalCrosses=12",
        "crossPct=0.4",
        "totalLongBalls=31",
        "accurateLongBalls=15",
        "longballPct=0.5",
        "blockedShots=0",
        "effectiveTackles=15",
        "totalTackles=20",
        "tacklePct=0.8",
        "interceptions=8",
        "effectiveClearance=14",
        "totalClearance=14"
      ]
    }
  ],
  "espnSamplePlays": []
}